freeqserver/__init__.py
freeqserver/freeqserver.py
freeqserver/__pycache__/__init__.cpython-312.pyc
freeqserver/__pycache__/freeqserver.cpython-312.pyc
freeq_server-0.0.19.dist-info/LICENSE
freeq_server-0.0.19.dist-info/METADATA
freeq_server-0.0.19.dist-info/WHEEL
freeq_server-0.0.19.dist-info/top_level.txt
freeq_server-0.0.19.dist-info/RECORD
