Metadata-Version: 2.1
Name: freeq-server
Version: 0.0.19
Summary: Zero-setup queue with e2e encryption for free in 1 line of code. Server part
Author-email: Viktor Hronec <zamr666@gmail.com>
License: Apache License
Project-URL: Homepage, https://github.com/hronecviktor/freeq-server
Project-URL: Bug Tracker, https://github.com/hronecviktor/freeq-server/issues
Keywords: queue,easy,message queue,zero-setup
Classifier: Programming Language :: Python :: 3
Classifier: License :: OSI Approved :: Apache Software License
Classifier: Operating System :: OS Independent
Requires-Python: >=3.7
License-File: LICENSE
Requires-Dist: annotated-types ==0.6.0
Requires-Dist: anyio ==3.7.1
Requires-Dist: certifi ==2023.11.17
Requires-Dist: click ==8.1.7
Requires-Dist: dnspython ==2.4.2
Requires-Dist: email-validator ==2.1.0.post1
Requires-Dist: fastapi[all] ==0.104.1
Requires-Dist: gunicorn ==21.2.0
Requires-Dist: h11 ==0.14.0
Requires-Dist: hiredis ==2.2.3
Requires-Dist: httpcore ==1.0.2
Requires-Dist: httptools ==0.6.1
Requires-Dist: httpx ==0.25.2
Requires-Dist: idna ==3.6
Requires-Dist: itsdangerous ==2.1.2
Requires-Dist: jinja2 ==3.1.2
Requires-Dist: markupsafe ==2.1.3
Requires-Dist: orjson ==3.9.10
Requires-Dist: packaging ==23.2
Requires-Dist: pydantic ==2.5.2
Requires-Dist: pydantic-core ==2.14.5
Requires-Dist: pydantic-extra-types ==2.1.0
Requires-Dist: pydantic-settings ==2.1.0
Requires-Dist: python-dotenv ==1.0.0
Requires-Dist: python-multipart ==0.0.6
Requires-Dist: pyyaml ==6.0.1
Requires-Dist: redis[hiredis] ==5.0.1
Requires-Dist: sniffio ==1.3.0
Requires-Dist: starlette ==0.27.0
Requires-Dist: typing-extensions ==4.9.0
Requires-Dist: ujson ==5.8.0
Requires-Dist: uvicorn[standard] ==0.24.0.post1
Requires-Dist: uvloop ==0.19.0
Requires-Dist: watchfiles ==0.21.0
Requires-Dist: websockets ==12.0
